semya/__about__.py
semya/__init__.py
semya-0.0.6.dist-info/METADATA
semya-0.0.6.dist-info/WHEEL
semya-0.0.6.dist-info/top_level.txt
semya-0.0.6.dist-info/RECORD
